globalmart_api_priyal/__init__.py
globalmart_api_priyal/api_dealer.py
globalmart_api_priyal-0.1.dist-info/METADATA
globalmart_api_priyal-0.1.dist-info/WHEEL
globalmart_api_priyal-0.1.dist-info/top_level.txt
globalmart_api_priyal-0.1.dist-info/RECORD
